txtai/__init__.py
txtai/client/__init__.py
txtai/client/api.py
txtai/client/embeddings.py
txtai/client/extractor.py
txtai/client/labels.py
txtai/client/segmentation.py
txtai/client/similarity.py
txtai/client/summary.py
txtai/client/textractor.py
txtai/client/transcription.py
txtai/client/translation.py
txtai/client/workflow.py
txtai_py-9.4.0.dist-info/LICENSE
txtai_py-9.4.0.dist-info/METADATA
txtai_py-9.4.0.dist-info/WHEEL
txtai_py-9.4.0.dist-info/top_level.txt
txtai_py-9.4.0.dist-info/RECORD
