Metadata-Version: 2.1
Name: txtai_py
Version: 9.4.0
Summary: Python client for txtai
Home-page: https://github.com/neuml/txtai.py
Author: NeuML
License: Apache 2.0: http://www.apache.org/licenses/LICENSE-2.0
Project-URL: Documentation, https://github.com/neuml/txtai.py
Project-URL: Issue Tracker, https://github.com/neuml/txtai.py/issues
Project-URL: Source Code, https://github.com/neuml/txtai.py
Keywords: search embedding machine-learning nlp
Classifier: License :: OSI Approved :: Apache Software License
Classifier: Operating System :: OS Independent
Classifier: Programming Language :: Python :: 3
Classifier: Topic :: Scientific/Engineering :: Artificial Intelligence
Classifier: Topic :: Software Development
Classifier: Topic :: Text Processing :: Indexing
Classifier: Topic :: Utilities
Requires-Python: >=3.10
License-File: LICENSE
Requires-Dist: aiohttp >=3.8.1
